README.rst
setup.py
django_markitup_widget.egg-info/PKG-INFO
django_markitup_widget.egg-info/SOURCES.txt
django_markitup_widget.egg-info/dependency_links.txt
django_markitup_widget.egg-info/requires.txt
django_markitup_widget.egg-info/top_level.txt
django_markitup_widget.egg-info/zip-safe
markitup/__init__.py
markitup/widgets.py
markitup/javascript/markitup/jquery.markitup.js
markitup/javascript/markitup/sets/default/set.js
markitup/javascript/markitup/sets/default/style.css
markitup/javascript/markitup/sets/default/images/bold.png
markitup/javascript/markitup/sets/default/images/clean.png
markitup/javascript/markitup/sets/default/images/image.png
markitup/javascript/markitup/sets/default/images/italic.png
markitup/javascript/markitup/sets/default/images/link.png
markitup/javascript/markitup/sets/default/images/picture.png
markitup/javascript/markitup/sets/default/images/preview.png
markitup/javascript/markitup/sets/default/images/stroke.png
markitup/javascript/markitup/skins/markitup/style.css
markitup/javascript/markitup/skins/markitup/images/bg-container.png
markitup/javascript/markitup/skins/markitup/images/bg-editor-bbcode.png
markitup/javascript/markitup/skins/markitup/images/bg-editor-dotclear.png
markitup/javascript/markitup/skins/markitup/images/bg-editor-html.png
markitup/javascript/markitup/skins/markitup/images/bg-editor-json.png
markitup/javascript/markitup/skins/markitup/images/bg-editor-markdown.png
markitup/javascript/markitup/skins/markitup/images/bg-editor-textile.png
markitup/javascript/markitup/skins/markitup/images/bg-editor-wiki.png
markitup/javascript/markitup/skins/markitup/images/bg-editor-xml.png
markitup/javascript/markitup/skins/markitup/images/bg-editor.png
markitup/javascript/markitup/skins/markitup/images/handle.png
markitup/javascript/markitup/skins/markitup/images/menu.png
markitup/javascript/markitup/skins/markitup/images/submenu.png
markitup/javascript/markitup/skins/simple/style.css
markitup/javascript/markitup/skins/simple/images/handle.png
markitup/javascript/markitup/skins/simple/images/menu.png
markitup/javascript/markitup/skins/simple/images/submenu.png
markitup/javascript/markitup/templates/preview.css
markitup/javascript/markitup/templates/preview.html
