Metadata-Version: 1.0
Name: django-markitup-widget
Version: 0.1rc3
Summary: django-markitup-widget is Django's textarea like widget for using markItUp! on textarea
Home-page: https://github.com/lambdalisue/django-markitup-widget
Author: Alisue
Author-email: lambdalisue@hashnote.net
License: BSD
Download-URL: https://github.com/lambdalisue/django-markitup-widget/tarball/master
Keywords: django widget textarea markItUp!
Platform: UNKNOWN
Classifier: Framework :: Django
Classifier: Intended Audience :: Developers
Classifier: License :: OSI Approved :: BSD License
Classifier: Programming Language :: Python
Classifier: Topic :: Internet :: WWW/HTTP
